searchconsole/__init__.py
searchconsole/account.py
searchconsole/auth.py
searchconsole/query.py
searchconsole/utils.py
searchconsole-0.1.0.dist-info/licenses/LICENSE
searchconsole-0.1.0.dist-info/METADATA
searchconsole-0.1.0.dist-info/WHEEL
searchconsole-0.1.0.dist-info/top_level.txt
searchconsole-0.1.0.dist-info/RECORD
