Metadata-Version: 2.4
Name: searchconsole
Version: 0.1.0
Summary: A wrapper for the Google Search Console API.
Author-email: Josh Carty <carty.josh@gmail.com>
License: MIT
License-File: LICENSE
Requires-Dist: google-api-python-client>=1.7.3
Requires-Dist: google-auth>=1.5.0
Requires-Dist: google-auth-oauthlib>=0.2.0
Requires-Dist: python-dateutil>=2.7.3
Provides-Extra: dev
Requires-Dist: tox>=4.0.0; extra == "dev"
Requires-Dist: tox-uv>=1.29.0; extra == "dev"
Requires-Dist: python-dotenv>=0.21.1; extra == "dev"
Requires-Dist: coverage>=7.0.0; extra == "dev"
Requires-Dist: ruff>=0.1.0; extra == "dev"
Provides-Extra: test
Requires-Dist: python-dotenv>=0.21.1; extra == "test"
Requires-Dist: coverage>=7.0.0; extra == "test"
Requires-Dist: ruff>=0.1.0; extra == "test"
Dynamic: license-file
